bffl/__init__.py
bffl/bffl.py
bffl/expressions.py
bffl/numduck.py
tests/__init__.py
tests/test_bffl.py
bffl-0.3.2.dist-info/LICENSE
bffl-0.3.2.dist-info/METADATA
bffl-0.3.2.dist-info/WHEEL
bffl-0.3.2.dist-info/top_level.txt
bffl-0.3.2.dist-info/RECORD
