Metadata-Version: 2.1
Name: bffl
Version: 0.3.2
Summary: A framework for structured bitfield processing
Home-page: https://github.com/kenseehart/bffl
Author: Ken Seehart
Author-email: ken@agi.green
Classifier: Programming Language :: Python :: 3
Classifier: License :: OSI Approved :: MIT License
Classifier: Operating System :: OS Independent
Requires-Python: >=3.6
License-File: LICENSE
Requires-Dist: libcst
